kappadata/__init__.py
kappadata/error_messages.py
kappadata/errors.py
kappadata/factory.py
kappadata/caching/__init__.py
kappadata/caching/cached_dataset.py
kappadata/caching/shared_dict_dataset.py
kappadata/collators/__init__.py
kappadata/collators/kd_dino_mask_collator.py
kappadata/collators/kd_ijepa_mask_collator.py
kappadata/collators/kd_mix_collator.py
kappadata/collators/pad_sequences_collator.py
kappadata/collators/base/__init__.py
kappadata/collators/base/kd_collator_base.py
kappadata/collators/base/kd_compose_collator.py
kappadata/collators/base/kd_single_collator.py
kappadata/collators/base/kd_single_collator_wrapper.py
kappadata/common/__init__.py
kappadata/common/collators/__init__.py
kappadata/common/collators/mae_finetune_mix_collator.py
kappadata/common/datasets/__init__.py
kappadata/common/datasets/kd_image_folder.py
kappadata/common/transforms/__init__.py
kappadata/common/transforms/byol_transforms.py
kappadata/common/transforms/imagenet_minaug_transforms.py
kappadata/common/transforms/imagenet_noaug_transforms.py
kappadata/common/transforms/mae_finetune_transform.py
kappadata/common/transforms/mugs_transforms.py
kappadata/common/transforms/norm/__init__.py
kappadata/common/transforms/norm/kd_audioset_norm.py
kappadata/common/transforms/norm/kd_cifar100_norm.py
kappadata/common/transforms/norm/kd_cifar10_norm.py
kappadata/common/transforms/norm/kd_esc50_norm.py
kappadata/common/transforms/norm/kd_image_net_norm.py
kappadata/common/transforms/norm/kd_sid_norm.py
kappadata/common/transforms/norm/kd_speech_ccommands_v1_norm.py
kappadata/common/transforms/norm/kd_speech_ccommands_v2_norm.py
kappadata/common/wrappers/__init__.py
kappadata/common/wrappers/sample_wrappers/__init__.py
kappadata/common/wrappers/sample_wrappers/byol_multi_view_wrapper.py
kappadata/common/wrappers/sample_wrappers/imagenet_minaug_multi_view_wrapper.py
kappadata/common/wrappers/sample_wrappers/imagenet_minaug_x_transform_wrapper.py
kappadata-1.4.15.dist-info/LICENSE
kappadata-1.4.15.dist-info/METADATA
kappadata-1.4.15.dist-info/WHEEL
kappadata-1.4.15.dist-info/top_level.txt
kappadata-1.4.15.dist-info/RECORD
