Metadata-Version: 2.1
Name: kappadata
Version: 1.4.15
Summary: pytorch dataset wrappers for in-memory caching
Home-page: https://github.com/BenediktAlkin/KappaData
Project-URL: Source Code, https://github.com/BenediktAlkin/KappaData
Project-URL: Bug Tracker, https://github.com/BenediktAlkin/KappaData/issues
Classifier: Programming Language :: Python :: 3
Classifier: License :: OSI Approved :: MIT License
Classifier: Operating System :: OS Independent
Requires-Python: >=3.6
License-File: LICENSE
Requires-Dist: torch
Requires-Dist: torchvision
Requires-Dist: Pillow
Requires-Dist: numpy
Requires-Dist: einops
Requires-Dist: joblib
Requires-Dist: timm
Requires-Dist: kappaschedules
